takumi_cli/__init__.py
takumi_cli/runner.py
takumi_cli/cmds/__init__.py
takumi_cli/cmds/_base.py
takumi_cli/cmds/deploy.py
takumi_cli/cmds/help.py
takumi_cli/cmds/serve.py
takumi_cli/cmds/shell.py
takumi_cli/deploy/__init__.py
takumi_cli/deploy/playbook/crontab.yml
takumi_cli/deploy/playbook/deploy.yml
takumi_cli/deploy/playbook/playbook.yml
takumi_cli/deploy/playbook/files/logrotate.j2
takumi_cli/deploy/playbook/files/rsyslog.j2
takumi_cli/deploy/playbook/files/supervisor.j2
takumi_cli-0.1.2.dist-info/DESCRIPTION.rst
takumi_cli-0.1.2.dist-info/entry_points.txt
takumi_cli-0.1.2.dist-info/METADATA
takumi_cli-0.1.2.dist-info/metadata.json
takumi_cli-0.1.2.dist-info/RECORD
takumi_cli-0.1.2.dist-info/top_level.txt
takumi_cli-0.1.2.dist-info/WHEEL
