Metadata-Version: 2.0
Name: takumi-cli
Version: 0.1.2
Summary: Takumi service framework command line toolkit
Home-page: https://github.com/elemecreativelab/takumi-cli
Author: Eleme Lab
Author-email: imaralla@icloud.com
License: UNKNOWN
Platform: UNKNOWN
Requires-Dist: takumi
Requires-Dist: takumi-ext
Requires-Dist: takumi-config
Requires-Dist: docopt
Requires-Dist: schema
Requires-Dist: gevent (>=1.2.1)
Requires-Dist: thriftpy
Requires-Dist: gunicorn
Provides-Extra: deploy
Requires-Dist: ansible (>=2.2.0.0); extra == 'deploy'
Provides-Extra: shell
Requires-Dist: takumi-client; extra == 'shell'
Requires-Dist: IPython; extra == 'shell'
